fiftyfive/__init__.py
fiftyfive/api.py
fiftyfive/decorators.py
fiftyfive/models.py
fiftyfive/requests.py
fiftyfive-0.2.0.dist-info/METADATA
fiftyfive-0.2.0.dist-info/WHEEL
fiftyfive-0.2.0.dist-info/licenses/LICENSE
fiftyfive-0.2.0.dist-info/RECORD
