Metadata-Version: 2.4
Name: fiftyfive
Version: 0.2.0
Summary: Python 3 package to retrieve EV charger data from 50five
Project-URL: Homepage, https://github.com/Crazy-Duck/fiftyfive
Project-URL: Bug Tracker, https://github.com/Crazy-Duck/fiftyfive/issues
License: GPLv3+
License-File: LICENSE
Classifier: License :: OSI Approved :: GNU General Public License v3 or later (GPLv3+)
Classifier: Programming Language :: Python :: 3.13
Classifier: Topic :: Home Automation
Requires-Python: >=3.13
Requires-Dist: aiohttp
